[
 {
  "default_value": null,
  "doc_type": "Lead",
  "docstatus": 0,
  "doctype": "Property Setter",
  "doctype_or_field": "DocField",
  "field_name": "fax",
  "modified": "2021-03-02 13:00:16.779869",
  "name": "Lead-fax-reqd",
  "parent": null,
  "parentfield": null,
  "parenttype": null,
  "property": "reqd",
  "property_type": "Check",
  "row_name": null,
  "value": "1"
 },
 {
  "default_value": null,
  "doc_type": "Lead",
  "docstatus": 0,
  "doctype": "Property Setter",
  "doctype_or_field": "DocField",
  "field_name": "contact_by",
  "modified": "2021-02-16 16:45:34.788765",
  "name": "Lead-contact_by-reqd",
  "parent": null,
  "parentfield": null,
  "parenttype": null,
  "property": "reqd",
  "property_type": "Check",
  "row_name": null,
  "value": "1"
 },
 {
  "default_value": null,
  "doc_type": "Lead",
  "docstatus": 0,
  "doctype": "Property Setter",
  "doctype_or_field": "DocField",
  "field_name": "contact_date",
  "modified": "2021-02-16 16:45:37.435183",
  "name": "Lead-contact_date-reqd",
  "parent": null,
  "parentfield": null,
  "parenttype": null,
  "property": "reqd",
  "property_type": "Check",
  "row_name": null,
  "value": "1"
 },
 {
  "default_value": null,
  "doc_type": "Lead",
  "docstatus": 0,
  "doctype": "Property Setter",
  "doctype_or_field": "DocField",
  "field_name": "ends_on",
  "modified": "2021-02-16 16:45:37.527644",
  "name": "Lead-ends_on-reqd",
  "parent": null,
  "parentfield": null,
  "parenttype": null,
  "property": "reqd",
  "property_type": "Check",
  "row_name": null,
  "value": "1"
 },
 {
  "default_value": null,
  "doc_type": "Lead",
  "docstatus": 0,
  "doctype": "Property Setter",
  "doctype_or_field": "DocField",
  "field_name": "notes",
  "modified": "2021-02-16 16:45:37.594773",
  "name": "Lead-notes-reqd",
  "parent": null,
  "parentfield": null,
  "parenttype": null,
  "property": "reqd",
  "property_type": "Check",
  "row_name": null,
  "value": "1"
 },
 {
  "default_value": null,
  "doc_type": "Lead",
  "docstatus": 0,
  "doctype": "Property Setter",
  "doctype_or_field": "DocField",
  "field_name": "phone",
  "modified": "2021-02-16 16:45:37.736384",
  "name": "Lead-phone-reqd",
  "parent": null,
  "parentfield": null,
  "parenttype": null,
  "property": "reqd",
  "property_type": "Check",
  "row_name": null,
  "value": "1"
 },
 {
  "default_value": null,
  "doc_type": "Lead",
  "docstatus": 0,
  "doctype": "Property Setter",
  "doctype_or_field": "DocField",
  "field_name": "mobile_no",
  "modified": "2021-02-16 16:45:37.789471",
  "name": "Lead-mobile_no-reqd",
  "parent": null,
  "parentfield": null,
  "parenttype": null,
  "property": "reqd",
  "property_type": "Check",
  "row_name": null,
  "value": "1"
 },
 {
  "default_value": null,
  "doc_type": "Employee",
  "docstatus": 0,
  "doctype": "Property Setter",
  "doctype_or_field": "DocField",
  "field_name": "naming_series",
  "modified": "2021-02-19 14:11:28.338671",
  "name": "Employee-naming_series-label",
  "parent": null,
  "parentfield": null,
  "parenttype": null,
  "property": "label",
  "property_type": "Data",
  "row_name": null,
  "value": "Emp ID"
 },
 {
  "default_value": null,
  "doc_type": "Production Plan",
  "docstatus": 0,
  "doctype": "Property Setter",
  "doctype_or_field": "DocField",
  "field_name": "project",
  "modified": "2021-08-26 10:47:47.866854",
  "name": "Production Plan-project-mandatory_depends_on",
  "parent": null,
  "parentfield": null,
  "parenttype": null,
  "property": "mandatory_depends_on",
  "property_type": "Data",
  "row_name": null,
  "value": "eval: doc.get_items_from == \"Sales Order\""
 },
 {
  "default_value": null,
  "doc_type": "Project",
  "docstatus": 0,
  "doctype": "Property Setter",
  "doctype_or_field": "DocField",
  "field_name": "gross_margin",
  "modified": "2021-12-21 17:12:54.534975",
  "name": "Project-gross_margin-hidden",
  "parent": null,
  "parentfield": null,
  "parenttype": null,
  "property": "hidden",
  "property_type": "Check",
  "row_name": null,
  "value": "1"
 },
 {
  "default_value": null,
  "doc_type": "Project",
  "docstatus": 0,
  "doctype": "Property Setter",
  "doctype_or_field": "DocField",
  "field_name": "per_gross_margin",
  "modified": "2021-12-21 17:12:55.310738",
  "name": "Project-per_gross_margin-hidden",
  "parent": null,
  "parentfield": null,
  "parenttype": null,
  "property": "hidden",
  "property_type": "Check",
  "row_name": null,
  "value": "1"
 },
 {
  "default_value": null,
  "doc_type": "Timesheet Detail",
  "docstatus": 0,
  "doctype": "Property Setter",
  "doctype_or_field": "DocField",
  "field_name": "hours",
  "modified": "2022-03-03 23:47:37.188192",
  "name": "Timesheet Detail-hours-label",
  "parent": null,
  "parentfield": null,
  "parenttype": null,
  "property": "label",
  "property_type": "Data",
  "row_name": null,
  "value": "Total Billing Hours"
 },
 {
  "default_value": null,
  "doc_type": "Timesheet Detail",
  "docstatus": 0,
  "doctype": "Property Setter",
  "doctype_or_field": "DocField",
  "field_name": "hours",
  "modified": "2022-03-03 23:58:28.940934",
  "name": "Timesheet Detail-hours-columns",
  "parent": null,
  "parentfield": null,
  "parenttype": null,
  "property": "columns",
  "property_type": "Int",
  "row_name": null,
  "value": "2"
 }
]